[
  {
    "bridge_balance_mohm": 0.0,
    "id": 396403051,
    "leak_pa": 0.0,
    "num_spikes": 0,
    "peak_deflection": null,
    "post_noise_rms_mv": 0.0,
    "post_vm_mv": 0.0,
    "pre_noise_rms_mv": 0.0,
    "pre_vm_mv": 0.0,
    "slow_noise_rms_mv": 0.0,
    "slow_vm_mv": 0.0,
    "specimen_id": 328031983,
    "stimulus_absolute_amplitude": 9.99999977648258,
    "stimulus_description": "EXTPSMOKET141203[0]",
    "stimulus_duration": 0.069995,
    "stimulus_interval": 0.05,
    "stimulus_name": "Test",
    "stimulus_relative_amplitude": 1.0,
    "stimulus_start_time": 0.03,
    "stimulus_units": "Volts",
    "sweep_number": 0,
    "vm_delta_mv": 0.0
  },
  {
    "bridge_balance_mohm": 0.0,
    "id": 396403053,
    "leak_pa": 0.0,
    "num_spikes": 0,
    "peak_deflection": null,
    "post_noise_rms_mv": 0.0,
    "post_vm_mv": 0.0,
    "pre_noise_rms_mv": 0.0,
    "pre_vm_mv": 0.0,
    "slow_noise_rms_mv": 0.0,
    "slow_vm_mv": 0.0,
    "specimen_id": 328031983,
    "stimulus_absolute_amplitude": 9.99999977648258,
    "stimulus_description": "EXTPINBATH141203[0]",
    "stimulus_duration": 0.069995,
    "stimulus_interval": 0.05,
    "stimulus_name": "Test",
    "stimulus_relative_amplitude": 1.0,
    "stimulus_start_time": 0.03,
    "stimulus_units": "Volts",
    "sweep_number": 1,
    "vm_delta_mv": 0.0
  },
  {
    "bridge_balance_mohm": 0.0,
    "id": 396403095,
    "leak_pa": 0.0,
    "num_spikes": 0,
    "peak_deflection": null,
    "post_noise_rms_mv": 0.0,
    "post_vm_mv": 0.0,
    "pre_noise_rms_mv": 0.0,
    "pre_vm_mv": 0.0,
    "slow_noise_rms_mv": 0.0,
    "slow_vm_mv": 0.0,
    "specimen_id": 328031983,
    "stimulus_absolute_amplitude": 9.99999977648258,
    "stimulus_description": "EXTPCllATT141203[0]",
    "stimulus_duration": 0.069995,
    "stimulus_interval": 0.05,
    "stimulus_name": "Test",
    "stimulus_relative_amplitude": 1.0,
    "stimulus_start_time": 0.03,
    "stimulus_units": "Volts",
    "sweep_number": 2,
    "vm_delta_mv": 0.0
  },
  {
    "bridge_balance_mohm": 0.0,
    "id": 396403117,
    "leak_pa": 0.0,
    "num_spikes": 0,
    "peak_deflection": null,
    "post_noise_rms_mv": 0.0,
    "post_vm_mv": 0.0,
    "pre_noise_rms_mv": 0.0,
    "pre_vm_mv": 0.0,
    "slow_noise_rms_mv": 0.0,
    "slow_vm_mv": 0.0,
    "specimen_id": 328031983,
    "stimulus_absolute_amplitude": 9.99999977648258,
    "stimulus_description": "EXTPBREAKN141203[0]",
    "stimulus_duration": 0.069995,
    "stimulus_interval": 0.05,
    "stimulus_name": "Test",
    "stimulus_relative_amplitude": 1.0,
    "stimulus_start_time": 0.03,
    "stimulus_units": "Volts",
    "sweep_number": 3,
    "vm_delta_mv": 0.0
  },
  {
    "bridge_balance_mohm": 13.0647125244141,
    "id": 396403139,
    "leak_pa": 0.0,
    "num_spikes": 7,
    "peak_deflection": null,
    "post_noise_rms_mv": 0.0,
    "post_vm_mv": 0.0,
    "pre_noise_rms_mv": 0.0361746363341808,
    "pre_vm_mv": -72.141975402832,
    "slow_noise_rms_mv": 0.118963569402695,
    "slow_vm_mv": -72.141975402832,
    "specimen_id": 328031983,
    "stimulus_absolute_amplitude": 800.000010681146,
    "stimulus_description": "C1RP25PR1S141203[0]",
    "stimulus_duration": 31.997495,
    "stimulus_interval": null,
    "stimulus_name": "Ramp",
    "stimulus_relative_amplitude": 1.0,
    "stimulus_start_time": 1.0225,
    "stimulus_units": "Amps",
    "sweep_number": 4,
    "vm_delta_mv": 0.0
  },
  {
    "bridge_balance_mohm": 13.0647125244141,
    "id": 396403164,
    "leak_pa": 0.0,
    "num_spikes": 7,
    "peak_deflection": null,
    "post_noise_rms_mv": 0.0,
    "post_vm_mv": 0.0,
    "pre_noise_rms_mv": 0.0407855361700058,
    "pre_vm_mv": -72.2067413330078,
    "slow_noise_rms_mv": 0.130963921546936,
    "slow_vm_mv": -72.2067413330078,
    "specimen_id": 328031983,
    "stimulus_absolute_amplitude": 800.000010681146,
    "stimulus_description": "C1RP25PR1S141203[0]",
    "stimulus_duration": 31.997495,
    "stimulus_interval": null,
    "stimulus_name": "Ramp",
    "stimulus_relative_amplitude": 1.0,
    "stimulus_start_time": 1.0225,
    "stimulus_units": "Amps",
    "sweep_number": 5,
    "vm_delta_mv": 0.0
  },
  {
    "bridge_balance_mohm": 13.0647125244141,
    "id": 396403189,
    "leak_pa": -1.9833652973175,
    "num_spikes": 5,
    "peak_deflection": null,
    "post_noise_rms_mv": 0.0,
    "post_vm_mv": 0.0,
    "pre_noise_rms_mv": 0.0374565646052361,
    "pre_vm_mv": -71.6890106201172,
    "slow_noise_rms_mv": 0.198225915431976,
    "slow_vm_mv": -71.6890106201172,
    "specimen_id": 328031983,
    "stimulus_absolute_amplitude": 800.000010681146,
    "stimulus_description": "C1RP25PR1S141203[0]",
    "stimulus_duration": 31.997495,
    "stimulus_interval": null,
    "stimulus_name": "Ramp",
    "stimulus_relative_amplitude": 1.0,
    "stimulus_start_time": 1.0225,
    "stimulus_units": "Amps",
    "sweep_number": 6,
    "vm_delta_mv": 0.0
  },
  {
    "bridge_balance_mohm": 13.0647125244141,
    "id": 396403214,
    "leak_pa": -1.9833652973175,
    "num_spikes": null,
    "peak_deflection": null,
    "post_noise_rms_mv": 0.0394350253045559,
    "post_vm_mv": -72.2421112060547,
    "pre_noise_rms_mv": 0.0428844317793846,
    "pre_vm_mv": -71.998779296875,
    "slow_noise_rms_mv": 0.106311209499836,
    "slow_vm_mv": -71.998779296875,
    "specimen_id": 328031983,
    "stimulus_absolute_amplitude": 100.000001335143,
    "stimulus_description": "C1SSCOARSE150112[0]",
    "stimulus_duration": 0.002995,
    "stimulus_interval": null,
    "stimulus_name": "Short Square",
    "stimulus_relative_amplitude": 1.0,
    "stimulus_start_time": 1.02,
    "stimulus_units": "Amps",
    "sweep_number": 7,
    "vm_delta_mv": 0.243331909179688
  },
  {
    "bridge_balance_mohm": 13.0647125244141,
    "id": 396403242,
    "leak_pa": -1.9833652973175,
    "num_spikes": null,
    "peak_deflection": null,
    "post_noise_rms_mv": 0.04711789265275,
    "post_vm_mv": -70.9061279296875,
    "pre_noise_rms_mv": 0.0395263135433197,
    "pre_vm_mv": -71.5359649658203,
    "slow_noise_rms_mv": 0.249390095472336,
    "slow_vm_mv": -71.5359649658203,
    "specimen_id": 328031983,
    "stimulus_absolute_amplitude": 200.000002670286,
    "stimulus_description": "C1SSCOARSE150112[1]",
    "stimulus_duration": 0.002995,
    "stimulus_interval": null,
    "stimulus_name": "Short Square",
    "stimulus_relative_amplitude": 1.0,
    "stimulus_start_time": 1.02,
    "stimulus_units": "Amps",
    "sweep_number": 8,
    "vm_delta_mv": 0.629837036132812
  },
  {
    "bridge_balance_mohm": 13.0647125244141,
    "id": 396403264,
    "leak_pa": -4.03071022033691,
    "num_spikes": null,
    "peak_deflection": null,
    "post_noise_rms_mv": 0.038884062319994,
    "post_vm_mv": -71.1364974975586,
    "pre_noise_rms_mv": 0.0443501062691212,
    "pre_vm_mv": -71.3531265258789,
    "slow_noise_rms_mv": 0.295836389064789,
    "slow_vm_mv": -71.3531265258789,
    "specimen_id": 328031983,
    "stimulus_absolute_amplitude": 299.999997066536,
    "stimulus_description": "C1SSCOARSE150112[2]",
    "stimulus_duration": 0.002995,
    "stimulus_interval": null,
    "stimulus_name": "Short Square",
    "stimulus_relative_amplitude": 1.0,
    "stimulus_start_time": 1.02,
    "stimulus_units": "Amps",
    "sweep_number": 9,
    "vm_delta_mv": 0.216629028320312
  },
  {
    "bridge_balance_mohm": 13.0647125244141,
    "id": 396403055,
    "leak_pa": -6.014075756073,
    "num_spikes": null,
    "peak_deflection": null,
    "post_noise_rms_mv": 0.0414383299648762,
    "post_vm_mv": -71.6499176025391,
    "pre_noise_rms_mv": 0.050156831741333,
    "pre_vm_mv": -71.9261932373047,
    "slow_noise_rms_mv": 0.234466299414635,
    "slow_vm_mv": -71.9261932373047,
    "specimen_id": 328031983,
    "stimulus_absolute_amplitude": 400.000005340573,
    "stimulus_description": "C1SSCOARSE150112[3]",
    "stimulus_duration": 0.002995,
    "stimulus_interval": null,
    "stimulus_name": "Short Square",
    "stimulus_relative_amplitude": 1.0,
    "stimulus_start_time": 1.02,
    "stimulus_units": "Amps",
    "sweep_number": 10,
    "vm_delta_mv": 0.276275634765625
  },
  {
    "bridge_balance_mohm": 13.0647125244141,
    "id": 396403065,
    "leak_pa": -6.014075756073,
    "num_spikes": null,
    "peak_deflection": null,
    "post_noise_rms_mv": 0.0438528321683407,
    "post_vm_mv": -72.2565765380859,
    "pre_noise_rms_mv": 0.0439997762441635,
    "pre_vm_mv": -72.5710372924805,
    "slow_noise_rms_mv": 0.211392015218735,
    "slow_vm_mv": -72.5710372924805,
    "specimen_id": 328031983,
    "stimulus_absolute_amplitude": 499.999985859034,
    "stimulus_description": "C1SSCOARSE150112[4]",
    "stimulus_duration": 0.002995,
    "stimulus_interval": null,
    "stimulus_name": "Short Square",
    "stimulus_relative_amplitude": 1.0,
    "stimulus_start_time": 1.02,
    "stimulus_units": "Amps",
    "sweep_number": 11,
    "vm_delta_mv": 0.314460754394531
  },
  {
    "bridge_balance_mohm": 13.0647125244141,
    "id": 396403067,
    "leak_pa": -6.014075756073,
    "num_spikes": 1,
    "peak_deflection": null,
    "post_noise_rms_mv": 0.0370055623352528,
    "post_vm_mv": -72.7092819213867,
    "pre_noise_rms_mv": 0.0322591215372086,
    "pre_vm_mv": -72.9489898681641,
    "slow_noise_rms_mv": 0.127216160297394,
    "slow_vm_mv": -72.9489898681641,
    "specimen_id": 328031983,
    "stimulus_absolute_amplitude": 599.999994133071,
    "stimulus_description": "C1SSCOARSE150112[5]",
    "stimulus_duration": 0.002995,
    "stimulus_interval": null,
    "stimulus_name": "Short Square",
    "stimulus_relative_amplitude": 1.0,
    "stimulus_start_time": 1.02,
    "stimulus_units": "Amps",
    "sweep_number": 12,
    "vm_delta_mv": 0.239707946777344
  },
  {
    "bridge_balance_mohm": 13.0647125244141,
    "id": 396403080,
    "leak_pa": -6.014075756073,
    "num_spikes": 1,
    "peak_deflection": null,
    "post_noise_rms_mv": 0.0402587540447712,
    "post_vm_mv": -71.6621017456055,
    "pre_noise_rms_mv": 0.0485980398952961,
    "pre_vm_mv": -72.1503067016602,
    "slow_noise_rms_mv": 0.211145773530006,
    "slow_vm_mv": -72.1503067016602,
    "specimen_id": 328031983,
    "stimulus_absolute_amplitude": 569.99999165086,
    "stimulus_description": "C1SSFINEST150112[0]",
    "stimulus_duration": 0.002995,
    "stimulus_interval": null,
    "stimulus_name": "Short Square",
    "stimulus_relative_amplitude": 5.7,
    "stimulus_start_time": 1.02,
    "stimulus_units": "Amps",
    "sweep_number": 14,
    "vm_delta_mv": 0.488204956054688
  },
  {
    "bridge_balance_mohm": 13.0647125244141,
    "id": 396403082,
    "leak_pa": -6.014075756073,
    "num_spikes": 1,
    "peak_deflection": null,
    "post_noise_rms_mv": 0.0360207334160805,
    "post_vm_mv": -72.2637252807617,
    "pre_noise_rms_mv": 0.0359452329576015,
    "pre_vm_mv": -71.3982467651367,
    "slow_noise_rms_mv": 0.188760846853256,
    "slow_vm_mv": -71.3982467651367,
    "specimen_id": 328031983,
    "stimulus_absolute_amplitude": 559.999990823457,
    "stimulus_description": "C1SSFINEST150112[0]",
    "stimulus_duration": 0.002995,
    "stimulus_interval": null,
    "stimulus_name": "Short Square",
    "stimulus_relative_amplitude": 5.6,
    "stimulus_start_time": 1.02,
    "stimulus_units": "Amps",
    "sweep_number": 15,
    "vm_delta_mv": 0.865478515625
  },
  {
    "bridge_balance_mohm": 13.0647125244141,
    "id": 396403084,
    "leak_pa": -6.014075756073,
    "num_spikes": 1,
    "peak_deflection": null,
    "post_noise_rms_mv": 0.0398042574524879,
    "post_vm_mv": -71.9088592529297,
    "pre_noise_rms_mv": 0.0424356758594513,
    "pre_vm_mv": -71.679313659668,
    "slow_noise_rms_mv": 0.253682166337967,
    "slow_vm_mv": -71.679313659668,
    "specimen_id": 328031983,
    "stimulus_absolute_amplitude": 549.999989996053,
    "stimulus_description": "C1SSFINEST150112[0]",
    "stimulus_duration": 0.002995,
    "stimulus_interval": null,
    "stimulus_name": "Short Square",
    "stimulus_relative_amplitude": 5.5,
    "stimulus_start_time": 1.02,
    "stimulus_units": "Amps",
    "sweep_number": 16,
    "vm_delta_mv": 0.229545593261719
  },
  {
    "bridge_balance_mohm": 13.0647125244141,
    "id": 396403086,
    "leak_pa": -6.014075756073,
    "num_spikes": null,
    "peak_deflection": null,
    "post_noise_rms_mv": 0.0367547422647476,
    "post_vm_mv": -71.2767028808594,
    "pre_noise_rms_mv": 0.0401284322142601,
    "pre_vm_mv": -71.1930770874023,
    "slow_noise_rms_mv": 0.170531630516052,
    "slow_vm_mv": -71.1930770874023,
    "specimen_id": 328031983,
    "stimulus_absolute_amplitude": 539.999989168649,
    "stimulus_description": "C1SSFINEST150112[0]",
    "stimulus_duration": 0.002995,
    "stimulus_interval": null,
    "stimulus_name": "Short Square",
    "stimulus_relative_amplitude": 5.4,
    "stimulus_start_time": 1.02,
    "stimulus_units": "Amps",
    "sweep_number": 17,
    "vm_delta_mv": 0.0836257934570312
  },
  {
    "bridge_balance_mohm": 13.0647125244141,
    "id": 396403089,
    "leak_pa": -6.014075756073,
    "num_spikes": null,
    "peak_deflection": null,
    "post_noise_rms_mv": 0.0445879325270653,
    "post_vm_mv": -72.0705108642578,
    "pre_noise_rms_mv": 0.0426558442413807,
    "pre_vm_mv": -72.019889831543,
    "slow_noise_rms_mv": 0.158579304814339,
    "slow_vm_mv": -72.019889831543,
    "specimen_id": 328031983,
    "stimulus_absolute_amplitude": 549.999989996053,
    "stimulus_description": "C1SSFINEST150112[0]",
    "stimulus_duration": 0.002995,
    "stimulus_interval": null,
    "stimulus_name": "Short Square",
    "stimulus_relative_amplitude": 5.5,
    "stimulus_start_time": 1.02,
    "stimulus_units": "Amps",
    "sweep_number": 18,
    "vm_delta_mv": 0.0506210327148438
  },
  {
    "bridge_balance_mohm": 13.0647125244141,
    "id": 396403092,
    "leak_pa": -6.014075756073,
    "num_spikes": null,
    "peak_deflection": null,
    "post_noise_rms_mv": 0.0432511605322361,
    "post_vm_mv": -72.2695617675781,
    "pre_noise_rms_mv": 0.0422132425010204,
    "pre_vm_mv": -71.9048156738281,
    "slow_noise_rms_mv": 0.121999122202396,
    "slow_vm_mv": -71.9048156738281,
    "specimen_id": 328031983,
    "stimulus_absolute_amplitude": 549.999989996053,
    "stimulus_description": "C1SSFINEST150112[0]",
    "stimulus_duration": 0.002995,
    "stimulus_interval": null,
    "stimulus_name": "Short Square",
    "stimulus_relative_amplitude": 5.5,
    "stimulus_start_time": 1.02,
    "stimulus_units": "Amps",
    "sweep_number": 19,
    "vm_delta_mv": 0.36474609375
  },
  {
    "bridge_balance_mohm": 13.0647125244141,
    "id": 396403097,
    "leak_pa": -9.98080635070801,
    "num_spikes": null,
    "peak_deflection": null,
    "post_noise_rms_mv": 0.0359154716134071,
    "post_vm_mv": -71.4286422729492,
    "pre_noise_rms_mv": 0.0368268191814423,
    "pre_vm_mv": -71.4418029785156,
    "slow_noise_rms_mv": 0.162111893296242,
    "slow_vm_mv": -71.4418029785156,
    "specimen_id": 328031983,
    "stimulus_absolute_amplitude": 559.999990823457,
    "stimulus_description": "C1SSFINEST150112[0]",
    "stimulus_duration": 0.002995,
    "stimulus_interval": null,
    "stimulus_name": "Short Square",
    "stimulus_relative_amplitude": 5.6,
    "stimulus_start_time": 1.02,
    "stimulus_units": "Amps",
    "sweep_number": 20,
    "vm_delta_mv": 0.0131607055664062
  },
  {
    "bridge_balance_mohm": 13.0647125244141,
    "id": 396403099,
    "leak_pa": -9.98080635070801,
    "num_spikes": null,
    "peak_deflection": null,
    "post_noise_rms_mv": 0.043843686580658,
    "post_vm_mv": -71.9833984375,
    "pre_noise_rms_mv": 0.0394806712865829,
    "pre_vm_mv": -72.5721817016602,
    "slow_noise_rms_mv": 0.248990818858147,
    "slow_vm_mv": -72.5721817016602,
    "specimen_id": 328031983,
    "stimulus_absolute_amplitude": 559.999990823457,
    "stimulus_description": "C1SSFINEST150112[0]",
    "stimulus_duration": 0.002995,
    "stimulus_interval": null,
    "stimulus_name": "Short Square",
    "stimulus_relative_amplitude": 5.6,
    "stimulus_start_time": 1.02,
    "stimulus_units": "Amps",
    "sweep_number": 21,
    "vm_delta_mv": 0.588783264160156
  },
  {
    "bridge_balance_mohm": 13.0647125244141,
    "id": 396403101,
    "leak_pa": -9.98080635070801,
    "num_spikes": null,
    "peak_deflection": null,
    "post_noise_rms_mv": 0.0475042723119259,
    "post_vm_mv": -72.2402877807617,
    "pre_noise_rms_mv": 0.0384840480983257,
    "pre_vm_mv": -72.5881652832031,
    "slow_noise_rms_mv": 0.191029995679855,
    "slow_vm_mv": -72.5881652832031,
    "specimen_id": 328031983,
    "stimulus_absolute_amplitude": 569.99999165086,
    "stimulus_description": "C1SSFINEST150112[0]",
    "stimulus_duration": 0.002995,
    "stimulus_interval": null,
    "stimulus_name": "Short Square",
    "stimulus_relative_amplitude": 5.7,
    "stimulus_start_time": 1.02,
    "stimulus_units": "Amps",
    "sweep_number": 22,
    "vm_delta_mv": 0.347877502441406
  },
  {
    "bridge_balance_mohm": 13.0647125244141,
    "id": 396403103,
    "leak_pa": -9.98080635070801,
    "num_spikes": 1,
    "peak_deflection": null,
    "post_noise_rms_mv": 0.0414940007030964,
    "post_vm_mv": -71.4937362670898,
    "pre_noise_rms_mv": 0.0371910147368908,
    "pre_vm_mv": -71.6399765014648,
    "slow_noise_rms_mv": 0.258382260799408,
    "slow_vm_mv": -71.6399765014648,
    "specimen_id": 328031983,
    "stimulus_absolute_amplitude": 579.999992478264,
    "stimulus_description": "C1SSFINEST150112[0]",
    "stimulus_duration": 0.002995,
    "stimulus_interval": null,
    "stimulus_name": "Short Square",
    "stimulus_relative_amplitude": 5.8,
    "stimulus_start_time": 1.02,
    "stimulus_units": "Amps",
    "sweep_number": 23,
    "vm_delta_mv": 0.146240234375
  },
  {
    "bridge_balance_mohm": 13.0647125244141,
    "id": 396403105,
    "leak_pa": -9.98080635070801,
    "num_spikes": 1,
    "peak_deflection": null,
    "post_noise_rms_mv": 0.0306398067623377,
    "post_vm_mv": -71.6856460571289,
    "pre_noise_rms_mv": 0.0405496135354042,
    "pre_vm_mv": -71.6483383178711,
    "slow_noise_rms_mv": 0.159496232867241,
    "slow_vm_mv": -71.6483383178711,
    "specimen_id": 328031983,
    "stimulus_absolute_amplitude": 579.999992478264,
    "stimulus_description": "C1SSFINEST150112[0]",
    "stimulus_duration": 0.002995,
    "stimulus_interval": null,
    "stimulus_name": "Short Square",
    "stimulus_relative_amplitude": 5.8,
    "stimulus_start_time": 1.02,
    "stimulus_units": "Amps",
    "sweep_number": 24,
    "vm_delta_mv": 0.0373077392578125
  },
  {
    "bridge_balance_mohm": 13.0647125244141,
    "id": 396403107,
    "leak_pa": -9.98080635070801,
    "num_spikes": 1,
    "peak_deflection": null,
    "post_noise_rms_mv": 0.0372276231646538,
    "post_vm_mv": -70.7910537719727,
    "pre_noise_rms_mv": 0.0455968640744686,
    "pre_vm_mv": -70.8903427124023,
    "slow_noise_rms_mv": 0.387670934200287,
    "slow_vm_mv": -70.8903427124023,
    "specimen_id": 328031983,
    "stimulus_absolute_amplitude": 579.999992478264,
    "stimulus_description": "C1SSFINEST150112[0]",
    "stimulus_duration": 0.002995,
    "stimulus_interval": null,
    "stimulus_name": "Short Square",
    "stimulus_relative_amplitude": 5.8,
    "stimulus_start_time": 1.02,
    "stimulus_units": "Amps",
    "sweep_number": 25,
    "vm_delta_mv": 0.0992889404296875
  },
  {
    "bridge_balance_mohm": 13.0647125244141,
    "id": 396403109,
    "leak_pa": -9.98080635070801,
    "num_spikes": 1,
    "peak_deflection": null,
    "post_noise_rms_mv": 0.0445637069642544,
    "post_vm_mv": -70.6720886230469,
    "pre_noise_rms_mv": 0.0415899828076363,
    "pre_vm_mv": -70.413688659668,
    "slow_noise_rms_mv": 0.111288756132126,
    "slow_vm_mv": -70.413688659668,
    "specimen_id": 328031983,
    "stimulus_absolute_amplitude": 579.999992478264,
    "stimulus_description": "C1SSFINEST150112[0]",
    "stimulus_duration": 0.002995,
    "stimulus_interval": null,
    "stimulus_name": "Short Square",
    "stimulus_relative_amplitude": 5.8,
    "stimulus_start_time": 1.02,
    "stimulus_units": "Amps",
    "sweep_number": 26,
    "vm_delta_mv": 0.258399963378906
  },
  {
    "bridge_balance_mohm": 13.0647125244141,
    "id": 396403111,
    "leak_pa": -9.98080635070801,
    "num_spikes": 1,
    "peak_deflection": null,
    "post_noise_rms_mv": 0.0376763865351677,
    "post_vm_mv": -71.2055969238281,
    "pre_noise_rms_mv": 0.0459927879273891,
    "pre_vm_mv": -70.7501678466797,
    "slow_noise_rms_mv": 0.27044802904129,
    "slow_vm_mv": -70.7501678466797,
    "specimen_id": 328031983,
    "stimulus_absolute_amplitude": 579.999992478264,
    "stimulus_description": "C1SSFINEST150112[0]",
    "stimulus_duration": 0.002995,
    "stimulus_interval": null,
    "stimulus_name": "Short Square",
    "stimulus_relative_amplitude": 5.8,
    "stimulus_start_time": 1.02,
    "stimulus_units": "Amps",
    "sweep_number": 27,
    "vm_delta_mv": 0.455429077148438
  },
  {
    "bridge_balance_mohm": 13.0647125244141,
    "id": 396403113,
    "leak_pa": -17.9782466888428,
    "num_spikes": null,
    "peak_deflection": -96.21875,
    "post_noise_rms_mv": 0.0427564941346645,
    "post_vm_mv": -71.8039474487305,
    "pre_noise_rms_mv": 0.0370356701314449,
    "pre_vm_mv": -72.5893478393555,
    "slow_noise_rms_mv": 0.225904151797295,
    "slow_vm_mv": -72.5893478393555,
    "specimen_id": 328031983,
    "stimulus_absolute_amplitude": -110.000002162547,
    "stimulus_description": "C1LSCOARSE150112[0]",
    "stimulus_duration": 0.999995,
    "stimulus_interval": null,
    "stimulus_name": "Long Square",
    "stimulus_relative_amplitude": 1.0,
    "stimulus_start_time": 1.02,
    "stimulus_units": "Amps",
    "sweep_number": 28,
    "vm_delta_mv": 0.785400390625
  },
  {
    "bridge_balance_mohm": 13.0647125244141,
    "id": 396403115,
    "leak_pa": -17.9782466888428,
    "num_spikes": null,
    "peak_deflection": -91.28125,
    "post_noise_rms_mv": 0.0404859632253647,
    "post_vm_mv": -71.3909683227539,
    "pre_noise_rms_mv": 0.0338039472699165,
    "pre_vm_mv": -71.7413482666016,
    "slow_noise_rms_mv": 0.116117805242538,
    "slow_vm_mv": -71.7413482666016,
    "specimen_id": 328031983,
    "stimulus_absolute_amplitude": -90.0000005077395,
    "stimulus_description": "C1LSCOARSE150112[1]",
    "stimulus_duration": 0.999995,
    "stimulus_interval": null,
    "stimulus_name": "Long Square",
    "stimulus_relative_amplitude": 1.0,
    "stimulus_start_time": 1.02,
    "stimulus_units": "Amps",
    "sweep_number": 29,
    "vm_delta_mv": 0.350379943847656
  },
  {
    "bridge_balance_mohm": 13.0647125244141,
    "id": 396403119,
    "leak_pa": -17.9782466888428,
    "num_spikes": null,
    "peak_deflection": -88.46875,
    "post_noise_rms_mv": 0.041722547262907,
    "post_vm_mv": -71.5534057617188,
    "pre_noise_rms_mv": 0.0363969467580318,
    "pre_vm_mv": -72.5245971679688,
    "slow_noise_rms_mv": 0.164201185107231,
    "slow_vm_mv": -72.5245971679688,
    "specimen_id": 328031983,
    "stimulus_absolute_amplitude": -69.9999988529321,
    "stimulus_description": "C1LSCOARSE150112[2]",
    "stimulus_duration": 0.999995,
    "stimulus_interval": null,
    "stimulus_name": "Long Square",
    "stimulus_relative_amplitude": 1.0,
    "stimulus_start_time": 1.02,
    "stimulus_units": "Amps",
    "sweep_number": 30,
    "vm_delta_mv": 0.97119140625
  },
  {
    "bridge_balance_mohm": 13.0647125244141,
    "id": 396403121,
    "leak_pa": -17.9782466888428,
    "num_spikes": null,
    "peak_deflection": -84.0312576293945,
    "post_noise_rms_mv": 0.0434964895248413,
    "post_vm_mv": -71.6549758911133,
    "pre_noise_rms_mv": 0.0367877371609211,
    "pre_vm_mv": -72.0468597412109,
    "slow_noise_rms_mv": 0.298403441905975,
    "slow_vm_mv": -72.0468597412109,
    "specimen_id": 328031983,
    "stimulus_absolute_amplitude": -50.0000006675716,
    "stimulus_description": "C1LSCOARSE150112[3]",
    "stimulus_duration": 0.999995,
    "stimulus_interval": null,
    "stimulus_name": "Long Square",
    "stimulus_relative_amplitude": 1.0,
    "stimulus_start_time": 1.02,
    "stimulus_units": "Amps",
    "sweep_number": 31,
    "vm_delta_mv": 0.391883850097656
  },
  {
    "bridge_balance_mohm": 13.0647125244141,
    "id": 396403123,
    "leak_pa": -17.9782466888428,
    "num_spikes": null,
    "peak_deflection": -79.53125,
    "post_noise_rms_mv": 0.0419393628835678,
    "post_vm_mv": -72.19140625,
    "pre_noise_rms_mv": 0.0282401442527771,
    "pre_vm_mv": -72.0043029785156,
    "slow_noise_rms_mv": 0.131295546889305,
    "slow_vm_mv": -72.0043029785156,
    "specimen_id": 328031983,
    "stimulus_absolute_amplitude": -29.9999990127642,
    "stimulus_description": "C1LSCOARSE150112[4]",
    "stimulus_duration": 0.999995,
    "stimulus_interval": null,
    "stimulus_name": "Long Square",
    "stimulus_relative_amplitude": 1.0,
    "stimulus_start_time": 1.02,
    "stimulus_units": "Amps",
    "sweep_number": 32,
    "vm_delta_mv": 0.187103271484375
  },
  {
    "bridge_balance_mohm": 13.0647125244141,
    "id": 396403125,
    "leak_pa": -17.9782466888428,
    "num_spikes": null,
    "peak_deflection": -75.3125,
    "post_noise_rms_mv": 0.0431409440934658,
    "post_vm_mv": -72.5735626220703,
    "pre_noise_rms_mv": 0.0401494316756725,
    "pre_vm_mv": -72.4957122802734,
    "slow_noise_rms_mv": 0.271216511726379,
    "slow_vm_mv": -72.4957122802734,
    "specimen_id": 328031983,
    "stimulus_absolute_amplitude": -9.99999996004197,
    "stimulus_description": "C1LSCOARSE150112[5]",
    "stimulus_duration": 0.999995,
    "stimulus_interval": null,
    "stimulus_name": "Long Square",
    "stimulus_relative_amplitude": 1.0,
    "stimulus_start_time": 1.02,
    "stimulus_units": "Amps",
    "sweep_number": 33,
    "vm_delta_mv": 0.077850341796875
  },
  {
    "bridge_balance_mohm": 13.0647125244141,
    "id": 396403127,
    "leak_pa": -15.9948825836182,
    "num_spikes": null,
    "peak_deflection": -69.8437576293945,
    "post_noise_rms_mv": 0.0364872142672539,
    "post_vm_mv": -72.8788833618164,
    "pre_noise_rms_mv": 0.042519424110651,
    "pre_vm_mv": -72.8209075927734,
    "slow_noise_rms_mv": 0.114969804883003,
    "slow_vm_mv": -72.8209075927734,
    "specimen_id": 328031983,
    "stimulus_absolute_amplitude": 9.99999996004197,
    "stimulus_description": "C1LSCOARSE150112[6]",
    "stimulus_duration": 0.999995,
    "stimulus_interval": null,
    "stimulus_name": "Long Square",
    "stimulus_relative_amplitude": 1.0,
    "stimulus_start_time": 1.02,
    "stimulus_units": "Amps",
    "sweep_number": 34,
    "vm_delta_mv": 0.0579757690429688
  },
  {
    "bridge_balance_mohm": 13.0647125244141,
    "id": 396403129,
    "leak_pa": -15.9948825836182,
    "num_spikes": null,
    "peak_deflection": -64.5937576293945,
    "post_noise_rms_mv": 0.0417355485260487,
    "post_vm_mv": -72.7710800170898,
    "pre_noise_rms_mv": 0.0401472970843315,
    "pre_vm_mv": -72.5180435180664,
    "slow_noise_rms_mv": 0.104088239371777,
    "slow_vm_mv": -72.5180435180664,
    "specimen_id": 328031983,
    "stimulus_absolute_amplitude": 29.9999990127642,
    "stimulus_description": "C1LSCOARSE150112[7]",
    "stimulus_duration": 0.999995,
    "stimulus_interval": null,
    "stimulus_name": "Long Square",
    "stimulus_relative_amplitude": 1.0,
    "stimulus_start_time": 1.02,
    "stimulus_units": "Amps",
    "sweep_number": 35,
    "vm_delta_mv": 0.253036499023438
  },
  {
    "bridge_balance_mohm": 13.0647125244141,
    "id": 396403131,
    "leak_pa": -15.9948825836182,
    "num_spikes": null,
    "peak_deflection": -59.2812538146973,
    "post_noise_rms_mv": 0.0461047850549221,
    "post_vm_mv": -72.1793365478516,
    "pre_noise_rms_mv": 0.0459622628986835,
    "pre_vm_mv": -72.6481781005859,
    "slow_noise_rms_mv": 0.122078940272331,
    "slow_vm_mv": -72.6481781005859,
    "specimen_id": 328031983,
    "stimulus_absolute_amplitude": 50.0000006675716,
    "stimulus_description": "C1LSCOARSE150112[8]",
    "stimulus_duration": 0.999995,
    "stimulus_interval": null,
    "stimulus_name": "Long Square",
    "stimulus_relative_amplitude": 1.0,
    "stimulus_start_time": 1.02,
    "stimulus_units": "Amps",
    "sweep_number": 36,
    "vm_delta_mv": 0.468841552734375
  },
  {
    "bridge_balance_mohm": 13.0647125244141,
    "id": 396403133,
    "leak_pa": -15.9948825836182,
    "num_spikes": null,
    "peak_deflection": -50.6875,
    "post_noise_rms_mv": 0.042423915117979,
    "post_vm_mv": -72.3773422241211,
    "pre_noise_rms_mv": 0.0424111410975456,
    "pre_vm_mv": -72.1389083862305,
    "slow_noise_rms_mv": 0.115337654948235,
    "slow_vm_mv": -72.1389083862305,
    "specimen_id": 328031983,
    "stimulus_absolute_amplitude": 69.9999988529321,
    "stimulus_description": "C1LSCOARSE150112[9]",
    "stimulus_duration": 0.999995,
    "stimulus_interval": null,
    "stimulus_name": "Long Square",
    "stimulus_relative_amplitude": 1.0,
    "stimulus_start_time": 1.02,
    "stimulus_units": "Amps",
    "sweep_number": 37,
    "vm_delta_mv": 0.238433837890625
  },
  {
    "bridge_balance_mohm": 13.0647125244141,
    "id": 396403135,
    "leak_pa": -15.9948825836182,
    "num_spikes": 3,
    "peak_deflection": null,
    "post_noise_rms_mv": 0.0386856533586979,
    "post_vm_mv": -72.40087890625,
    "pre_noise_rms_mv": 0.0454463623464108,
    "pre_vm_mv": -72.3581390380859,
    "slow_noise_rms_mv": 0.130550697445869,
    "slow_vm_mv": -72.3581390380859,
    "specimen_id": 328031983,
    "stimulus_absolute_amplitude": 90.0000005077395,
    "stimulus_description": "C1LSCOARSE150112[10]",
    "stimulus_duration": 0.999995,
    "stimulus_interval": null,
    "stimulus_name": "Long Square",
    "stimulus_relative_amplitude": 1.0,
    "stimulus_start_time": 1.02,
    "stimulus_units": "Amps",
    "sweep_number": 38,
    "vm_delta_mv": 0.0427398681640625
  },
  {
    "bridge_balance_mohm": 13.0647125244141,
    "id": 396403137,
    "leak_pa": -15.9948825836182,
    "num_spikes": 15,
    "peak_deflection": null,
    "post_noise_rms_mv": 0.0432382822036743,
    "post_vm_mv": -71.8058242797852,
    "pre_noise_rms_mv": 0.0388374924659729,
    "pre_vm_mv": -72.088623046875,
    "slow_noise_rms_mv": 0.126067072153091,
    "slow_vm_mv": -72.088623046875,
    "specimen_id": 328031983,
    "stimulus_absolute_amplitude": 110.000002162547,
    "stimulus_description": "C1LSCOARSE150112[11]",
    "stimulus_duration": 0.999995,
    "stimulus_interval": null,
    "stimulus_name": "Long Square",
    "stimulus_relative_amplitude": 1.0,
    "stimulus_start_time": 1.02,
    "stimulus_units": "Amps",
    "sweep_number": 39,
    "vm_delta_mv": 0.282798767089844
  },
  {
    "bridge_balance_mohm": 13.0647125244141,
    "id": 396403141,
    "leak_pa": -15.9948825836182,
    "num_spikes": 26,
    "peak_deflection": null,
    "post_noise_rms_mv": 0.0373169668018818,
    "post_vm_mv": -72.144416809082,
    "pre_noise_rms_mv": 0.0388108231127262,
    "pre_vm_mv": -71.5738830566406,
    "slow_noise_rms_mv": 0.0990946292877197,
    "slow_vm_mv": -71.5738830566406,
    "specimen_id": 328031983,
    "stimulus_absolute_amplitude": 129.99999687846,
    "stimulus_description": "C1LSCOARSE150112[12]",
    "stimulus_duration": 0.999995,
    "stimulus_interval": null,
    "stimulus_name": "Long Square",
    "stimulus_relative_amplitude": 1.0,
    "stimulus_start_time": 1.02,
    "stimulus_units": "Amps",
    "sweep_number": 40,
    "vm_delta_mv": 0.570533752441406
  },
  {
    "bridge_balance_mohm": 13.0647125244141,
    "id": 396403143,
    "leak_pa": -15.9948825836182,
    "num_spikes": 36,
    "peak_deflection": null,
    "post_noise_rms_mv": 0.0414021126925945,
    "post_vm_mv": -71.6118011474609,
    "pre_noise_rms_mv": 0.0385362580418587,
    "pre_vm_mv": -71.4488220214844,
    "slow_noise_rms_mv": 0.269967317581177,
    "slow_vm_mv": -71.4488220214844,
    "specimen_id": 328031983,
    "stimulus_absolute_amplitude": 149.999998533268,
    "stimulus_description": "C1LSCOARSE150112[13]",
    "stimulus_duration": 0.999995,
    "stimulus_interval": null,
    "stimulus_name": "Long Square",
    "stimulus_relative_amplitude": 1.0,
    "stimulus_start_time": 1.02,
    "stimulus_units": "Amps",
    "sweep_number": 41,
    "vm_delta_mv": 0.162979125976562
  },
  {
    "bridge_balance_mohm": 13.0647125244141,
    "id": 396403145,
    "leak_pa": -19.0019207000732,
    "num_spikes": 44,
    "peak_deflection": null,
    "post_noise_rms_mv": 0.0448252521455288,
    "post_vm_mv": -71.9261169433594,
    "pre_noise_rms_mv": 0.0426624156534672,
    "pre_vm_mv": -71.5305023193359,
    "slow_noise_rms_mv": 0.14018902182579,
    "slow_vm_mv": -71.5305023193359,
    "specimen_id": 328031983,
    "stimulus_absolute_amplitude": 170.000000188075,
    "stimulus_description": "C1LSCOARSE150112[14]",
    "stimulus_duration": 0.999995,
    "stimulus_interval": null,
    "stimulus_name": "Long Square",
    "stimulus_relative_amplitude": 1.0,
    "stimulus_start_time": 1.02,
    "stimulus_units": "Amps",
    "sweep_number": 42,
    "vm_delta_mv": 0.395614624023438
  },
  {
    "bridge_balance_mohm": 13.0647125244141,
    "id": 396403147,
    "leak_pa": -19.0019207000732,
    "num_spikes": 54,
    "peak_deflection": null,
    "post_noise_rms_mv": 0.0281596574932337,
    "post_vm_mv": -72.0881118774414,
    "pre_noise_rms_mv": 0.0368111096322536,
    "pre_vm_mv": -71.1799087524414,
    "slow_noise_rms_mv": 0.0903209522366524,
    "slow_vm_mv": -71.1799087524414,
    "specimen_id": 328031983,
    "stimulus_absolute_amplitude": 190.000001842883,
    "stimulus_description": "C1LSCOARSE150112[15]",
    "stimulus_duration": 0.999995,
    "stimulus_interval": null,
    "stimulus_name": "Long Square",
    "stimulus_relative_amplitude": 1.0,
    "stimulus_start_time": 1.02,
    "stimulus_units": "Amps",
    "sweep_number": 43,
    "vm_delta_mv": 0.908203125
  },
  {
    "bridge_balance_mohm": 13.0647125244141,
    "id": 396403154,
    "leak_pa": -19.0019207000732,
    "num_spikes": 73,
    "peak_deflection": null,
    "post_noise_rms_mv": 0.0415235981345177,
    "post_vm_mv": -72.0954971313477,
    "pre_noise_rms_mv": 0.0414184033870697,
    "pre_vm_mv": -70.9671325683594,
    "slow_noise_rms_mv": 0.0984922274947166,
    "slow_vm_mv": -70.9671325683594,
    "specimen_id": 328031983,
    "stimulus_absolute_amplitude": 230.000005152498,
    "stimulus_description": "C1LSCOARSE150112[17]",
    "stimulus_duration": 0.999995,
    "stimulus_interval": null,
    "stimulus_name": "Long Square",
    "stimulus_relative_amplitude": 1.0,
    "stimulus_start_time": 1.02,
    "stimulus_units": "Amps",
    "sweep_number": 45,
    "vm_delta_mv": 1.12836456298828
  },
  {
    "bridge_balance_mohm": 13.0647125244141,
    "id": 396403156,
    "leak_pa": -20.9852848052979,
    "num_spikes": null,
    "peak_deflection": -40.96875,
    "post_noise_rms_mv": 0.039472121745348,
    "post_vm_mv": -71.4915771484375,
    "pre_noise_rms_mv": 0.0371131785213947,
    "pre_vm_mv": -71.5604629516602,
    "slow_noise_rms_mv": 0.0985956192016602,
    "slow_vm_mv": -71.5604629516602,
    "specimen_id": 328031983,
    "stimulus_absolute_amplitude": 79.9999996803358,
    "stimulus_description": "C1LSFINEST150112[0]",
    "stimulus_duration": 0.999995,
    "stimulus_interval": null,
    "stimulus_name": "Long Square",
    "stimulus_relative_amplitude": 0.8,
    "stimulus_start_time": 1.02,
    "stimulus_units": "Amps",
    "sweep_number": 46,
    "vm_delta_mv": 0.0688858032226562
  },
  {
    "bridge_balance_mohm": 13.0647125244141,
    "id": 396403158,
    "leak_pa": -28.0230312347412,
    "num_spikes": null,
    "peak_deflection": -39.875,
    "post_noise_rms_mv": 0.0405195988714695,
    "post_vm_mv": -72.2068176269531,
    "pre_noise_rms_mv": 0.0387547798454762,
    "pre_vm_mv": -72.2823715209961,
    "slow_noise_rms_mv": 0.119938008487225,
    "slow_vm_mv": -72.2823715209961,
    "specimen_id": 328031983,
    "stimulus_absolute_amplitude": 90.0000005077395,
    "stimulus_description": "C1LSFINEST150112[0]",
    "stimulus_duration": 0.999995,
    "stimulus_interval": null,
    "stimulus_name": "Long Square",
    "stimulus_relative_amplitude": 0.9,
    "stimulus_start_time": 1.02,
    "stimulus_units": "Amps",
    "sweep_number": 47,
    "vm_delta_mv": 0.0755538940429688
  },
  {
    "bridge_balance_mohm": 13.0647125244141,
    "id": 396403160,
    "leak_pa": -28.0230312347412,
    "num_spikes": 2,
    "peak_deflection": null,
    "post_noise_rms_mv": 0.0396779254078865,
    "post_vm_mv": -73.0850677490234,
    "pre_noise_rms_mv": 0.041486382484436,
    "pre_vm_mv": -72.8648681640625,
    "slow_noise_rms_mv": 0.333966165781021,
    "slow_vm_mv": -72.8648681640625,
    "specimen_id": 328031983,
    "stimulus_absolute_amplitude": 100.000001335143,
    "stimulus_description": "C1LSFINEST150112[0]",
    "stimulus_duration": 0.999995,
    "stimulus_interval": null,
    "stimulus_name": "Long Square",
    "stimulus_relative_amplitude": 1.0,
    "stimulus_start_time": 1.02,
    "stimulus_units": "Amps",
    "sweep_number": 48,
    "vm_delta_mv": 0.220199584960938
  },
  {
    "bridge_balance_mohm": 13.0647125244141,
    "id": 396403162,
    "leak_pa": -25.9756889343262,
    "num_spikes": 2,
    "peak_deflection": null,
    "post_noise_rms_mv": 0.0421756766736507,
    "post_vm_mv": -72.4350814819336,
    "pre_noise_rms_mv": 0.0404854379594326,
    "pre_vm_mv": -72.4465560913086,
    "slow_noise_rms_mv": 0.152716919779778,
    "slow_vm_mv": -72.4465560913086,
    "specimen_id": 328031983,
    "stimulus_absolute_amplitude": 100.000001335143,
    "stimulus_description": "C1LSFINEST150112[0]",
    "stimulus_duration": 0.999995,
    "stimulus_interval": null,
    "stimulus_name": "Long Square",
    "stimulus_relative_amplitude": 1.0,
    "stimulus_start_time": 1.02,
    "stimulus_units": "Amps",
    "sweep_number": 49,
    "vm_delta_mv": 0.011474609375
  },
  {
    "bridge_balance_mohm": 13.0647125244141,
    "id": 396403166,
    "leak_pa": -25.9756889343262,
    "num_spikes": 1,
    "peak_deflection": null,
    "post_noise_rms_mv": 0.0452471598982811,
    "post_vm_mv": -72.2659606933594,
    "pre_noise_rms_mv": 0.0373097956180573,
    "pre_vm_mv": -72.4278869628906,
    "slow_noise_rms_mv": 0.122907191514969,
    "slow_vm_mv": -72.4278869628906,
    "specimen_id": 328031983,
    "stimulus_absolute_amplitude": 100.000001335143,
    "stimulus_description": "C1LSFINEST150112[0]",
    "stimulus_duration": 0.999995,
    "stimulus_interval": null,
    "stimulus_name": "Long Square",
    "stimulus_relative_amplitude": 1.0,
    "stimulus_start_time": 1.02,
    "stimulus_units": "Amps",
    "sweep_number": 50,
    "vm_delta_mv": 0.16192626953125
  },
  {
    "bridge_balance_mohm": 13.0647125244141,
    "id": 396403169,
    "leak_pa": -25.9756889343262,
    "num_spikes": 114,
    "peak_deflection": null,
    "post_noise_rms_mv": 0.0336899198591709,
    "post_vm_mv": -73.3636016845703,
    "pre_noise_rms_mv": 0.0380770117044449,
    "pre_vm_mv": -72.6635284423828,
    "slow_noise_rms_mv": 0.120320290327072,
    "slow_vm_mv": -72.6635284423828,
    "specimen_id": 328031983,
    "stimulus_absolute_amplitude": 231.749994195063,
    "stimulus_description": "C1NSSEED_1150112[0]",
    "stimulus_duration": 18.999995,
    "stimulus_interval": 8.0,
    "stimulus_name": "Noise 1",
    "stimulus_relative_amplitude": 1.0,
    "stimulus_start_time": 2.02,
    "stimulus_units": "Amps",
    "sweep_number": 51,
    "vm_delta_mv": 0.7000732421875
  },
  {
    "bridge_balance_mohm": 13.0647125244141,
    "id": 396403172,
    "leak_pa": -23.9923229217529,
    "num_spikes": 119,
    "peak_deflection": null,
    "post_noise_rms_mv": 0.0366740040481091,
    "post_vm_mv": -72.1736526489258,
    "pre_noise_rms_mv": 0.0400102064013481,
    "pre_vm_mv": -71.9922943115234,
    "slow_noise_rms_mv": 0.0826681703329086,
    "slow_vm_mv": -71.9922943115234,
    "specimen_id": 328031983,
    "stimulus_absolute_amplitude": 235.750002852697,
    "stimulus_description": "C1NSSEED_2150112[0]",
    "stimulus_duration": 18.999995,
    "stimulus_interval": 8.0,
    "stimulus_name": "Noise 2",
    "stimulus_relative_amplitude": 1.0,
    "stimulus_start_time": 2.02,
    "stimulus_units": "Amps",
    "sweep_number": 52,
    "vm_delta_mv": 0.181358337402344
  },
  {
    "bridge_balance_mohm": 13.0647125244141,
    "id": 396403175,
    "leak_pa": -25.9756889343262,
    "num_spikes": 118,
    "peak_deflection": null,
    "post_noise_rms_mv": 0.0449087619781494,
    "post_vm_mv": -71.9504776000977,
    "pre_noise_rms_mv": 0.0427974686026573,
    "pre_vm_mv": -71.6195373535156,
    "slow_noise_rms_mv": 0.151314079761505,
    "slow_vm_mv": -71.6195373535156,
    "specimen_id": 328031983,
    "stimulus_absolute_amplitude": 231.749994195063,
    "stimulus_description": "C1NSSEED_1150112[0]",
    "stimulus_duration": 18.999995,
    "stimulus_interval": 8.0,
    "stimulus_name": "Noise 1",
    "stimulus_relative_amplitude": 1.0,
    "stimulus_start_time": 2.02,
    "stimulus_units": "Amps",
    "sweep_number": 53,
    "vm_delta_mv": 0.330940246582031
  },
  {
    "bridge_balance_mohm": 13.0647125244141,
    "id": 396403177,
    "leak_pa": -26.9993591308594,
    "num_spikes": 119,
    "peak_deflection": null,
    "post_noise_rms_mv": 0.0408962517976761,
    "post_vm_mv": -72.7608413696289,
    "pre_noise_rms_mv": 0.0351160131394863,
    "pre_vm_mv": -72.2556915283203,
    "slow_noise_rms_mv": 0.336589425802231,
    "slow_vm_mv": -72.2556915283203,
    "specimen_id": 328031983,
    "stimulus_absolute_amplitude": 235.750002852697,
    "stimulus_description": "C1NSSEED_2150112[0]",
    "stimulus_duration": 18.999995,
    "stimulus_interval": 8.0,
    "stimulus_name": "Noise 2",
    "stimulus_relative_amplitude": 1.0,
    "stimulus_start_time": 2.02,
    "stimulus_units": "Amps",
    "sweep_number": 54,
    "vm_delta_mv": 0.505149841308594
  },
  {
    "bridge_balance_mohm": 13.0647125244141,
    "id": 396403179,
    "leak_pa": -26.9993591308594,
    "num_spikes": 124,
    "peak_deflection": null,
    "post_noise_rms_mv": 0.0320832766592503,
    "post_vm_mv": -72.9516830444336,
    "pre_noise_rms_mv": 0.0349565669894218,
    "pre_vm_mv": -72.1586685180664,
    "slow_noise_rms_mv": 0.138756334781647,
    "slow_vm_mv": -72.1586685180664,
    "specimen_id": 328031983,
    "stimulus_absolute_amplitude": 231.749994195063,
    "stimulus_description": "C1NSSEED_1150112[0]",
    "stimulus_duration": 18.999995,
    "stimulus_interval": 8.0,
    "stimulus_name": "Noise 1",
    "stimulus_relative_amplitude": 1.0,
    "stimulus_start_time": 2.02,
    "stimulus_units": "Amps",
    "sweep_number": 55,
    "vm_delta_mv": 0.793014526367188
  },
  {
    "bridge_balance_mohm": 13.0647125244141,
    "id": 396403185,
    "leak_pa": -26.9993591308594,
    "num_spikes": 121,
    "peak_deflection": null,
    "post_noise_rms_mv": 0.033473014831543,
    "post_vm_mv": -74.2190551757812,
    "pre_noise_rms_mv": 0.0437109768390656,
    "pre_vm_mv": -72.8346862792969,
    "slow_noise_rms_mv": 0.105471268296242,
    "slow_vm_mv": -72.8346862792969,
    "specimen_id": 328031983,
    "stimulus_absolute_amplitude": 235.750002852697,
    "stimulus_description": "C1NSSEED_2150112[0]",
    "stimulus_duration": 18.999995,
    "stimulus_interval": 8.0,
    "stimulus_name": "Noise 2",
    "stimulus_relative_amplitude": 1.0,
    "stimulus_start_time": 2.02,
    "stimulus_units": "Amps",
    "sweep_number": 58,
    "vm_delta_mv": 1.38436889648438
  },
  {
    "bridge_balance_mohm": 13.0647125244141,
    "id": 396403191,
    "leak_pa": -25.0159950256348,
    "num_spikes": null,
    "peak_deflection": null,
    "post_noise_rms_mv": 0.0388054437935352,
    "post_vm_mv": -72.900993347168,
    "pre_noise_rms_mv": 0.0349384061992168,
    "pre_vm_mv": -72.5321731567383,
    "slow_noise_rms_mv": 0.259992212057114,
    "slow_vm_mv": -72.5321731567383,
    "specimen_id": 328031983,
    "stimulus_absolute_amplitude": -200.000002670286,
    "stimulus_description": "C1SQCAPCHK141203[0]",
    "stimulus_duration": 7.218495,
    "stimulus_interval": 0.2005,
    "stimulus_name": "Square - 0.5ms Subthreshold",
    "stimulus_relative_amplitude": 1.0,
    "stimulus_start_time": 0.8215,
    "stimulus_units": "Amps",
    "sweep_number": 60,
    "vm_delta_mv": 0.368820190429688
  },
  {
    "bridge_balance_mohm": 13.0647125244141,
    "id": 396403193,
    "leak_pa": -22.9686489105225,
    "num_spikes": null,
    "peak_deflection": null,
    "post_noise_rms_mv": 0.0363554768264294,
    "post_vm_mv": -71.7498931884766,
    "pre_noise_rms_mv": 0.0419261492788792,
    "pre_vm_mv": -71.9721527099609,
    "slow_noise_rms_mv": 0.307722866535187,
    "slow_vm_mv": -71.9721527099609,
    "specimen_id": 328031983,
    "stimulus_absolute_amplitude": -200.000002670286,
    "stimulus_description": "C1SQCAPCHK141203[0]",
    "stimulus_duration": 7.218495,
    "stimulus_interval": 0.2005,
    "stimulus_name": "Square - 0.5ms Subthreshold",
    "stimulus_relative_amplitude": 1.0,
    "stimulus_start_time": 0.8215,
    "stimulus_units": "Amps",
    "sweep_number": 61,
    "vm_delta_mv": 0.222259521484375
  },
  {
    "bridge_balance_mohm": 13.0647125244141,
    "id": 396403195,
    "leak_pa": -22.9686489105225,
    "num_spikes": 3,
    "peak_deflection": null,
    "post_noise_rms_mv": 0.0423152558505535,
    "post_vm_mv": -72.0836563110352,
    "pre_noise_rms_mv": 0.0376591198146343,
    "pre_vm_mv": -71.7806015014648,
    "slow_noise_rms_mv": 0.127893090248108,
    "slow_vm_mv": -71.7806015014648,
    "specimen_id": 328031983,
    "stimulus_absolute_amplitude": 100.000001335143,
    "stimulus_description": "C2SQRHELNG150112[0]",
    "stimulus_duration": 1.999995,
    "stimulus_interval": null,
    "stimulus_name": "Square - 2s Suprathreshold",
    "stimulus_relative_amplitude": 1.0,
    "stimulus_start_time": 1.02,
    "stimulus_units": "Amps",
    "sweep_number": 62,
    "vm_delta_mv": 0.303054809570312
  },
  {
    "bridge_balance_mohm": 13.0647125244141,
    "id": 396403198,
    "leak_pa": -22.9686489105225,
    "num_spikes": 2,
    "peak_deflection": null,
    "post_noise_rms_mv": 0.0467218086123466,
    "post_vm_mv": -72.649543762207,
    "pre_noise_rms_mv": 0.0394339896738529,
    "pre_vm_mv": -72.0431213378906,
    "slow_noise_rms_mv": 0.143787890672684,
    "slow_vm_mv": -72.0431213378906,
    "specimen_id": 328031983,
    "stimulus_absolute_amplitude": 100.000001335143,
    "stimulus_description": "C2SQRHELNG150112[0]",
    "stimulus_duration": 1.999995,
    "stimulus_interval": null,
    "stimulus_name": "Square - 2s Suprathreshold",
    "stimulus_relative_amplitude": 1.0,
    "stimulus_start_time": 1.02,
    "stimulus_units": "Amps",
    "sweep_number": 63,
    "vm_delta_mv": 0.606422424316406
  },
  {
    "bridge_balance_mohm": 13.0647125244141,
    "id": 396403201,
    "leak_pa": -22.9686489105225,
    "num_spikes": 2,
    "peak_deflection": null,
    "post_noise_rms_mv": 0.0407812409102917,
    "post_vm_mv": -72.3847885131836,
    "pre_noise_rms_mv": 0.040042407810688,
    "pre_vm_mv": -72.5602340698242,
    "slow_noise_rms_mv": 0.186105236411095,
    "slow_vm_mv": -72.5602340698242,
    "specimen_id": 328031983,
    "stimulus_absolute_amplitude": 100.000001335143,
    "stimulus_description": "C2SQRHELNG150112[0]",
    "stimulus_duration": 1.999995,
    "stimulus_interval": null,
    "stimulus_name": "Square - 2s Suprathreshold",
    "stimulus_relative_amplitude": 1.0,
    "stimulus_start_time": 1.02,
    "stimulus_units": "Amps",
    "sweep_number": 64,
    "vm_delta_mv": 0.175445556640625
  },
  {
    "bridge_balance_mohm": 13.0647125244141,
    "id": 396403204,
    "leak_pa": -22.9686489105225,
    "num_spikes": 3,
    "peak_deflection": null,
    "post_noise_rms_mv": 0.040226049721241,
    "post_vm_mv": -72.392204284668,
    "pre_noise_rms_mv": 0.0379049181938171,
    "pre_vm_mv": -72.3027038574219,
    "slow_noise_rms_mv": 0.24644248187542,
    "slow_vm_mv": -72.3027038574219,
    "specimen_id": 328031983,
    "stimulus_absolute_amplitude": 100.000001335143,
    "stimulus_description": "C2SQRHELNG150112[0]",
    "stimulus_duration": 1.999995,
    "stimulus_interval": null,
    "stimulus_name": "Square - 2s Suprathreshold",
    "stimulus_relative_amplitude": 1.0,
    "stimulus_start_time": 1.02,
    "stimulus_units": "Amps",
    "sweep_number": 65,
    "vm_delta_mv": 0.0895004272460938
  },
  {
    "bridge_balance_mohm": 13.0647125244141,
    "id": 396403206,
    "leak_pa": -22.9686489105225,
    "num_spikes": 12,
    "peak_deflection": null,
    "post_noise_rms_mv": 0.0438801795244217,
    "post_vm_mv": -71.7087860107422,
    "pre_noise_rms_mv": 0.0426511019468307,
    "pre_vm_mv": -71.6459884643555,
    "slow_noise_rms_mv": 0.11679208278656,
    "slow_vm_mv": -71.6459884643555,
    "specimen_id": 328031983,
    "stimulus_absolute_amplitude": 139.999997705864,
    "stimulus_description": "C2SQRHELNG150112[0]",
    "stimulus_duration": 1.999995,
    "stimulus_interval": null,
    "stimulus_name": "Square - 2s Suprathreshold",
    "stimulus_relative_amplitude": 1.4,
    "stimulus_start_time": 1.02,
    "stimulus_units": "Amps",
    "sweep_number": 66,
    "vm_delta_mv": 0.0627975463867188
  },
  {
    "bridge_balance_mohm": 13.0647125244141,
    "id": 396403208,
    "leak_pa": -25.9756889343262,
    "num_spikes": 30,
    "peak_deflection": null,
    "post_noise_rms_mv": 0.0374382399022579,
    "post_vm_mv": -72.9786682128906,
    "pre_noise_rms_mv": 0.0372784100472927,
    "pre_vm_mv": -72.6302490234375,
    "slow_noise_rms_mv": 0.124114654958248,
    "slow_vm_mv": -72.6302490234375,
    "specimen_id": 328031983,
    "stimulus_absolute_amplitude": 139.999997705864,
    "stimulus_description": "C2SQRHELNG150112[0]",
    "stimulus_duration": 1.999995,
    "stimulus_interval": null,
    "stimulus_name": "Square - 2s Suprathreshold",
    "stimulus_relative_amplitude": 1.4,
    "stimulus_start_time": 1.02,
    "stimulus_units": "Amps",
    "sweep_number": 67,
    "vm_delta_mv": 0.348419189453125
  },
  {
    "bridge_balance_mohm": 13.0647125244141,
    "id": 396403210,
    "leak_pa": -25.0159950256348,
    "num_spikes": 39,
    "peak_deflection": null,
    "post_noise_rms_mv": 0.0307796094566584,
    "post_vm_mv": -73.0643920898438,
    "pre_noise_rms_mv": 0.0402636229991913,
    "pre_vm_mv": -72.3361129760742,
    "slow_noise_rms_mv": 0.120719358325005,
    "slow_vm_mv": -72.3361129760742,
    "specimen_id": 328031983,
    "stimulus_absolute_amplitude": 139.999997705864,
    "stimulus_description": "C2SQRHELNG150112[0]",
    "stimulus_duration": 1.999995,
    "stimulus_interval": null,
    "stimulus_name": "Square - 2s Suprathreshold",
    "stimulus_relative_amplitude": 1.4,
    "stimulus_start_time": 1.02,
    "stimulus_units": "Amps",
    "sweep_number": 68,
    "vm_delta_mv": 0.728279113769531
  },
  {
    "bridge_balance_mohm": 13.0647125244141,
    "id": 396403212,
    "leak_pa": -23.9923229217529,
    "num_spikes": 54,
    "peak_deflection": null,
    "post_noise_rms_mv": 0.0395949333906174,
    "post_vm_mv": -73.4989242553711,
    "pre_noise_rms_mv": 0.0367439426481724,
    "pre_vm_mv": -72.5887832641602,
    "slow_noise_rms_mv": 0.0926852002739906,
    "slow_vm_mv": -72.5887832641602,
    "specimen_id": 328031983,
    "stimulus_absolute_amplitude": 139.999997705864,
    "stimulus_description": "C2SQRHELNG150112[0]",
    "stimulus_duration": 1.999995,
    "stimulus_interval": null,
    "stimulus_name": "Square - 2s Suprathreshold",
    "stimulus_relative_amplitude": 1.4,
    "stimulus_start_time": 1.02,
    "stimulus_units": "Amps",
    "sweep_number": 69,
    "vm_delta_mv": 0.910140991210938
  },
  {
    "bridge_balance_mohm": 13.0647125244141,
    "id": 396403218,
    "leak_pa": -22.9686489105225,
    "num_spikes": 106,
    "peak_deflection": null,
    "post_noise_rms_mv": 0.0439652018249035,
    "post_vm_mv": -73.9285736083984,
    "pre_noise_rms_mv": 0.0444035269320011,
    "pre_vm_mv": -72.2549438476562,
    "slow_noise_rms_mv": 0.115485794842243,
    "slow_vm_mv": -72.2549438476562,
    "specimen_id": 328031983,
    "stimulus_absolute_amplitude": 180.000001015479,
    "stimulus_description": "C2SQRHELNG150112[0]",
    "stimulus_duration": 1.999995,
    "stimulus_interval": null,
    "stimulus_name": "Square - 2s Suprathreshold",
    "stimulus_relative_amplitude": 1.8,
    "stimulus_start_time": 1.02,
    "stimulus_units": "Amps",
    "sweep_number": 71,
    "vm_delta_mv": 1.67362976074219
  },
  {
    "bridge_balance_mohm": 13.0647125244141,
    "id": 396403222,
    "leak_pa": -22.0089569091797,
    "num_spikes": 109,
    "peak_deflection": null,
    "post_noise_rms_mv": 0.0404617227613926,
    "post_vm_mv": -73.68017578125,
    "pre_noise_rms_mv": 0.0415285602211952,
    "pre_vm_mv": -72.0072937011719,
    "slow_noise_rms_mv": 0.123733699321747,
    "slow_vm_mv": -72.0072937011719,
    "specimen_id": 328031983,
    "stimulus_absolute_amplitude": 180.000001015479,
    "stimulus_description": "C2SQRHELNG150112[0]",
    "stimulus_duration": 1.999995,
    "stimulus_interval": null,
    "stimulus_name": "Square - 2s Suprathreshold",
    "stimulus_relative_amplitude": 1.8,
    "stimulus_start_time": 1.02,
    "stimulus_units": "Amps",
    "sweep_number": 73,
    "vm_delta_mv": 1.67288208007812
  },
  {
    "bridge_balance_mohm": 13.308913230896,
    "id": 396403228,
    "leak_pa": -22.9686489105225,
    "num_spikes": 331,
    "peak_deflection": null,
    "post_noise_rms_mv": 0.040605966001749,
    "post_vm_mv": -72.8513412475586,
    "pre_noise_rms_mv": 0.0377151072025299,
    "pre_vm_mv": -72.7282791137695,
    "slow_noise_rms_mv": 0.139297023415565,
    "slow_vm_mv": -72.7282791137695,
    "specimen_id": 328031983,
    "stimulus_absolute_amplitude": 338.999994742295,
    "stimulus_description": "C2NSRMPRH2150120[0]",
    "stimulus_duration": 31.99997,
    "stimulus_interval": null,
    "stimulus_name": "Ramp to Rheobase",
    "stimulus_relative_amplitude": 1.0,
    "stimulus_start_time": 2.020025,
    "stimulus_units": "Amps",
    "sweep_number": 75,
    "vm_delta_mv": 0.123062133789062
  },
  {
    "bridge_balance_mohm": 13.308913230896,
    "id": 396403230,
    "leak_pa": -20.9852848052979,
    "num_spikes": 355,
    "peak_deflection": null,
    "post_noise_rms_mv": 0.0405123829841614,
    "post_vm_mv": -72.0710830688477,
    "pre_noise_rms_mv": 0.0376372672617435,
    "pre_vm_mv": -72.2515258789062,
    "slow_noise_rms_mv": 0.173389762639999,
    "slow_vm_mv": -72.2515258789062,
    "specimen_id": 328031983,
    "stimulus_absolute_amplitude": 338.999994742295,
    "stimulus_description": "C2NSRMPRH2150120[0]",
    "stimulus_duration": 31.99997,
    "stimulus_interval": null,
    "stimulus_name": "Ramp to Rheobase",
    "stimulus_relative_amplitude": 1.0,
    "stimulus_start_time": 2.020025,
    "stimulus_units": "Amps",
    "sweep_number": 76,
    "vm_delta_mv": 0.180442810058594
  },
  {
    "bridge_balance_mohm": 13.308913230896,
    "id": 396403236,
    "leak_pa": -22.9686489105225,
    "num_spikes": 3,
    "peak_deflection": null,
    "post_noise_rms_mv": 0.058923065662384,
    "post_vm_mv": -72.6801223754883,
    "pre_noise_rms_mv": 0.0453935712575912,
    "pre_vm_mv": -72.1397018432617,
    "slow_noise_rms_mv": 0.314097821712494,
    "slow_vm_mv": -72.1397018432617,
    "specimen_id": 328031983,
    "stimulus_absolute_amplitude": 579.999992478264,
    "stimulus_description": "C2SSTRIPLE141203[0]",
    "stimulus_duration": 0.016995,
    "stimulus_interval": 0.007,
    "stimulus_name": "Short Square - Triple",
    "stimulus_relative_amplitude": 5.8,
    "stimulus_start_time": 2.02,
    "stimulus_units": "Amps",
    "sweep_number": 77,
    "vm_delta_mv": 0.540420532226562
  },
  {
    "bridge_balance_mohm": 13.308913230896,
    "id": 396403238,
    "leak_pa": -22.9686489105225,
    "num_spikes": 3,
    "peak_deflection": null,
    "post_noise_rms_mv": 0.0444761142134666,
    "post_vm_mv": -72.5539855957031,
    "pre_noise_rms_mv": 0.0386089757084846,
    "pre_vm_mv": -72.3328704833984,
    "slow_noise_rms_mv": 0.233087822794914,
    "slow_vm_mv": -72.3328704833984,
    "specimen_id": 328031983,
    "stimulus_absolute_amplitude": 579.999992478264,
    "stimulus_description": "C2SSTRIPLE141203[1]",
    "stimulus_duration": 0.024995,
    "stimulus_interval": 0.011,
    "stimulus_name": "Short Square - Triple",
    "stimulus_relative_amplitude": 5.8,
    "stimulus_start_time": 2.02,
    "stimulus_units": "Amps",
    "sweep_number": 78,
    "vm_delta_mv": 0.221115112304688
  },
  {
    "bridge_balance_mohm": 13.308913230896,
    "id": 396403240,
    "leak_pa": -22.9686489105225,
    "num_spikes": 3,
    "peak_deflection": null,
    "post_noise_rms_mv": 0.0425649248063564,
    "post_vm_mv": -72.6395034790039,
    "pre_noise_rms_mv": 0.0397016033530235,
    "pre_vm_mv": -72.2215270996094,
    "slow_noise_rms_mv": 0.155518814921379,
    "slow_vm_mv": -72.2215270996094,
    "specimen_id": 328031983,
    "stimulus_absolute_amplitude": 579.999992478264,
    "stimulus_description": "C2SSTRIPLE141203[2]",
    "stimulus_duration": 0.032995,
    "stimulus_interval": 0.015,
    "stimulus_name": "Short Square - Triple",
    "stimulus_relative_amplitude": 5.8,
    "stimulus_start_time": 2.02,
    "stimulus_units": "Amps",
    "sweep_number": 79,
    "vm_delta_mv": 0.417976379394531
  },
  {
    "bridge_balance_mohm": 13.308913230896,
    "id": 396403244,
    "leak_pa": -22.9686489105225,
    "num_spikes": 4,
    "peak_deflection": null,
    "post_noise_rms_mv": 0.0472524575889111,
    "post_vm_mv": -72.6325073242188,
    "pre_noise_rms_mv": 0.0354257076978683,
    "pre_vm_mv": -72.2074279785156,
    "slow_noise_rms_mv": 0.182734295725822,
    "slow_vm_mv": -72.2074279785156,
    "specimen_id": 328031983,
    "stimulus_absolute_amplitude": 579.999992478264,
    "stimulus_description": "C2SSTRIPLE141203[3]",
    "stimulus_duration": 0.040995,
    "stimulus_interval": 0.019,
    "stimulus_name": "Short Square - Triple",
    "stimulus_relative_amplitude": 5.8,
    "stimulus_start_time": 2.02,
    "stimulus_units": "Amps",
    "sweep_number": 80,
    "vm_delta_mv": 0.425079345703125
  },
  {
    "bridge_balance_mohm": 13.308913230896,
    "id": 396403246,
    "leak_pa": -22.9686489105225,
    "num_spikes": 3,
    "peak_deflection": null,
    "post_noise_rms_mv": 0.0395501665771008,
    "post_vm_mv": -73.2471466064453,
    "pre_noise_rms_mv": 0.0338632203638554,
    "pre_vm_mv": -73.0319366455078,
    "slow_noise_rms_mv": 0.132344737648964,
    "slow_vm_mv": -73.0319366455078,
    "specimen_id": 328031983,
    "stimulus_absolute_amplitude": 579.999992478264,
    "stimulus_description": "C2SSTRIPLE141203[4]",
    "stimulus_duration": 0.048995,
    "stimulus_interval": 0.023,
    "stimulus_name": "Short Square - Triple",
    "stimulus_relative_amplitude": 5.8,
    "stimulus_start_time": 2.02,
    "stimulus_units": "Amps",
    "sweep_number": 81,
    "vm_delta_mv": 0.2152099609375
  },
  {
    "bridge_balance_mohm": 13.308913230896,
    "id": 396403248,
    "leak_pa": -22.9686489105225,
    "num_spikes": 3,
    "peak_deflection": null,
    "post_noise_rms_mv": 0.0407718978822231,
    "post_vm_mv": -73.484016418457,
    "pre_noise_rms_mv": 0.041623193770647,
    "pre_vm_mv": -72.8441619873047,
    "slow_noise_rms_mv": 0.241176843643188,
    "slow_vm_mv": -72.8441619873047,
    "specimen_id": 328031983,
    "stimulus_absolute_amplitude": 579.999992478264,
    "stimulus_description": "C2SSTRIPLE141203[5]",
    "stimulus_duration": 0.056995,
    "stimulus_interval": 0.027,
    "stimulus_name": "Short Square - Triple",
    "stimulus_relative_amplitude": 5.8,
    "stimulus_start_time": 2.02,
    "stimulus_units": "Amps",
    "sweep_number": 82,
    "vm_delta_mv": 0.639854431152344
  },
  {
    "bridge_balance_mohm": 13.308913230896,
    "id": 396403250,
    "leak_pa": -22.9686489105225,
    "num_spikes": 3,
    "peak_deflection": null,
    "post_noise_rms_mv": 0.0630214437842369,
    "post_vm_mv": -73.1936721801758,
    "pre_noise_rms_mv": 0.038450863212347,
    "pre_vm_mv": -72.828727722168,
    "slow_noise_rms_mv": 0.107814289629459,
    "slow_vm_mv": -72.828727722168,
    "specimen_id": 328031983,
    "stimulus_absolute_amplitude": 579.999992478264,
    "stimulus_description": "C2SSTRIPLE141203[6]",
    "stimulus_duration": 0.064995,
    "stimulus_interval": 0.031,
    "stimulus_name": "Short Square - Triple",
    "stimulus_relative_amplitude": 5.8,
    "stimulus_start_time": 2.02,
    "stimulus_units": "Amps",
    "sweep_number": 83,
    "vm_delta_mv": 0.364944458007812
  },
  {
    "bridge_balance_mohm": 13.308913230896,
    "id": 396403252,
    "leak_pa": -20.9852848052979,
    "num_spikes": 3,
    "peak_deflection": null,
    "post_noise_rms_mv": 0.0372819676995277,
    "post_vm_mv": -73.2944488525391,
    "pre_noise_rms_mv": 0.0429004915058613,
    "pre_vm_mv": -72.6534194946289,
    "slow_noise_rms_mv": 0.160766005516052,
    "slow_vm_mv": -72.6534194946289,
    "specimen_id": 328031983,
    "stimulus_absolute_amplitude": 579.999992478264,
    "stimulus_description": "C2SSTRIPLE141203[7]",
    "stimulus_duration": 0.072995,
    "stimulus_interval": 0.035,
    "stimulus_name": "Short Square - Triple",
    "stimulus_relative_amplitude": 5.8,
    "stimulus_start_time": 2.02,
    "stimulus_units": "Amps",
    "sweep_number": 84,
    "vm_delta_mv": 0.641029357910156
  },
  {
    "bridge_balance_mohm": 13.308913230896,
    "id": 396403254,
    "leak_pa": -20.9852848052979,
    "num_spikes": 3,
    "peak_deflection": null,
    "post_noise_rms_mv": 0.0428708232939243,
    "post_vm_mv": -72.6967468261719,
    "pre_noise_rms_mv": 0.0371950678527355,
    "pre_vm_mv": -72.2444686889648,
    "slow_noise_rms_mv": 0.121256612241268,
    "slow_vm_mv": -72.2444686889648,
    "specimen_id": 328031983,
    "stimulus_absolute_amplitude": 579.999992478264,
    "stimulus_description": "C2SSTRIPLE141203[0]",
    "stimulus_duration": 0.016995,
    "stimulus_interval": 0.007,
    "stimulus_name": "Short Square - Triple",
    "stimulus_relative_amplitude": 5.8,
    "stimulus_start_time": 2.02,
    "stimulus_units": "Amps",
    "sweep_number": 85,
    "vm_delta_mv": 0.452278137207031
  },
  {
    "bridge_balance_mohm": 13.308913230896,
    "id": 396403256,
    "leak_pa": -20.9852848052979,
    "num_spikes": 3,
    "peak_deflection": null,
    "post_noise_rms_mv": 0.0392357259988785,
    "post_vm_mv": -72.7685165405273,
    "pre_noise_rms_mv": 0.0325462259352207,
    "pre_vm_mv": -72.2666702270508,
    "slow_noise_rms_mv": 0.165561333298683,
    "slow_vm_mv": -72.2666702270508,
    "specimen_id": 328031983,
    "stimulus_absolute_amplitude": 579.999992478264,
    "stimulus_description": "C2SSTRIPLE141203[1]",
    "stimulus_duration": 0.024995,
    "stimulus_interval": 0.011,
    "stimulus_name": "Short Square - Triple",
    "stimulus_relative_amplitude": 5.8,
    "stimulus_start_time": 2.02,
    "stimulus_units": "Amps",
    "sweep_number": 86,
    "vm_delta_mv": 0.501846313476562
  },
  {
    "bridge_balance_mohm": 13.308913230896,
    "id": 396403258,
    "leak_pa": -20.9852848052979,
    "num_spikes": 3,
    "peak_deflection": null,
    "post_noise_rms_mv": 0.0349042229354382,
    "post_vm_mv": -72.0671157836914,
    "pre_noise_rms_mv": 0.0432591661810875,
    "pre_vm_mv": -71.6307830810547,
    "slow_noise_rms_mv": 0.366798162460327,
    "slow_vm_mv": -71.6307830810547,
    "specimen_id": 328031983,
    "stimulus_absolute_amplitude": 579.999992478264,
    "stimulus_description": "C2SSTRIPLE141203[2]",
    "stimulus_duration": 0.032995,
    "stimulus_interval": 0.015,
    "stimulus_name": "Short Square - Triple",
    "stimulus_relative_amplitude": 5.8,
    "stimulus_start_time": 2.02,
    "stimulus_units": "Amps",
    "sweep_number": 87,
    "vm_delta_mv": 0.436332702636719
  },
  {
    "bridge_balance_mohm": 13.308913230896,
    "id": 396403260,
    "leak_pa": -20.9852848052979,
    "num_spikes": 3,
    "peak_deflection": null,
    "post_noise_rms_mv": 0.039005059748888,
    "post_vm_mv": -72.6775970458984,
    "pre_noise_rms_mv": 0.0372392311692238,
    "pre_vm_mv": -72.2687225341797,
    "slow_noise_rms_mv": 0.133113503456116,
    "slow_vm_mv": -72.2687225341797,
    "specimen_id": 328031983,
    "stimulus_absolute_amplitude": 579.999992478264,
    "stimulus_description": "C2SSTRIPLE141203[3]",
    "stimulus_duration": 0.040995,
    "stimulus_interval": 0.019,
    "stimulus_name": "Short Square - Triple",
    "stimulus_relative_amplitude": 5.8,
    "stimulus_start_time": 2.02,
    "stimulus_units": "Amps",
    "sweep_number": 88,
    "vm_delta_mv": 0.40887451171875
  },
  {
    "bridge_balance_mohm": 13.308913230896,
    "id": 396403262,
    "leak_pa": -20.9852848052979,
    "num_spikes": 3,
    "peak_deflection": null,
    "post_noise_rms_mv": 0.0384802035987377,
    "post_vm_mv": -72.4975662231445,
    "pre_noise_rms_mv": 0.0430658906698227,
    "pre_vm_mv": -72.017707824707,
    "slow_noise_rms_mv": 0.127536490559578,
    "slow_vm_mv": -72.017707824707,
    "specimen_id": 328031983,
    "stimulus_absolute_amplitude": 579.999992478264,
    "stimulus_description": "C2SSTRIPLE141203[4]",
    "stimulus_duration": 0.048995,
    "stimulus_interval": 0.023,
    "stimulus_name": "Short Square - Triple",
    "stimulus_relative_amplitude": 5.8,
    "stimulus_start_time": 2.02,
    "stimulus_units": "Amps",
    "sweep_number": 89,
    "vm_delta_mv": 0.4798583984375
  },
  {
    "bridge_balance_mohm": 13.308913230896,
    "id": 396403266,
    "leak_pa": -20.9852848052979,
    "num_spikes": 3,
    "peak_deflection": null,
    "post_noise_rms_mv": 0.0388197973370552,
    "post_vm_mv": -72.5580291748047,
    "pre_noise_rms_mv": 0.0422713086009026,
    "pre_vm_mv": -72.0785293579102,
    "slow_noise_rms_mv": 0.177977323532104,
    "slow_vm_mv": -72.0785293579102,
    "specimen_id": 328031983,
    "stimulus_absolute_amplitude": 579.999992478264,
    "stimulus_description": "C2SSTRIPLE141203[5]",
    "stimulus_duration": 0.056995,
    "stimulus_interval": 0.027,
    "stimulus_name": "Short Square - Triple",
    "stimulus_relative_amplitude": 5.8,
    "stimulus_start_time": 2.02,
    "stimulus_units": "Amps",
    "sweep_number": 90,
    "vm_delta_mv": 0.479499816894531
  },
  {
    "bridge_balance_mohm": 13.308913230896,
    "id": 396403268,
    "leak_pa": -20.9852848052979,
    "num_spikes": 3,
    "peak_deflection": null,
    "post_noise_rms_mv": 0.0375249162316322,
    "post_vm_mv": -72.8487777709961,
    "pre_noise_rms_mv": 0.0371419042348862,
    "pre_vm_mv": -72.4142456054688,
    "slow_noise_rms_mv": 0.110211730003357,
    "slow_vm_mv": -72.4142456054688,
    "specimen_id": 328031983,
    "stimulus_absolute_amplitude": 579.999992478264,
    "stimulus_description": "C2SSTRIPLE141203[6]",
    "stimulus_duration": 0.064995,
    "stimulus_interval": 0.031,
    "stimulus_name": "Short Square - Triple",
    "stimulus_relative_amplitude": 5.8,
    "stimulus_start_time": 2.02,
    "stimulus_units": "Amps",
    "sweep_number": 91,
    "vm_delta_mv": 0.434532165527344
  },
  {
    "bridge_balance_mohm": 13.308913230896,
    "id": 396403270,
    "leak_pa": -20.9852848052979,
    "num_spikes": 3,
    "peak_deflection": null,
    "post_noise_rms_mv": 0.040752362459898,
    "post_vm_mv": -72.8218078613281,
    "pre_noise_rms_mv": 0.0374133512377739,
    "pre_vm_mv": -72.4386749267578,
    "slow_noise_rms_mv": 0.14994814991951,
    "slow_vm_mv": -72.4386749267578,
    "specimen_id": 328031983,
    "stimulus_absolute_amplitude": 579.999992478264,
    "stimulus_description": "C2SSTRIPLE141203[7]",
    "stimulus_duration": 0.072995,
    "stimulus_interval": 0.035,
    "stimulus_name": "Short Square - Triple",
    "stimulus_relative_amplitude": 5.8,
    "stimulus_start_time": 2.02,
    "stimulus_units": "Amps",
    "sweep_number": 92,
    "vm_delta_mv": 0.383132934570312
  },
  {
    "bridge_balance_mohm": 13.308913230896,
    "id": 396403272,
    "leak_pa": -20.9852848052979,
    "num_spikes": 3,
    "peak_deflection": null,
    "post_noise_rms_mv": 0.0417313389480114,
    "post_vm_mv": -72.5632019042969,
    "pre_noise_rms_mv": 0.0382178500294685,
    "pre_vm_mv": -71.9916229248047,
    "slow_noise_rms_mv": 0.203682526946068,
    "slow_vm_mv": -71.9916229248047,
    "specimen_id": 328031983,
    "stimulus_absolute_amplitude": 579.999992478264,
    "stimulus_description": "C2SSTRIPLE141203[0]",
    "stimulus_duration": 0.016995,
    "stimulus_interval": 0.007,
    "stimulus_name": "Short Square - Triple",
    "stimulus_relative_amplitude": 5.8,
    "stimulus_start_time": 2.02,
    "stimulus_units": "Amps",
    "sweep_number": 93,
    "vm_delta_mv": 0.571578979492188
  },
  {
    "bridge_balance_mohm": 13.308913230896,
    "id": 396403274,
    "leak_pa": -20.9852848052979,
    "num_spikes": 3,
    "peak_deflection": null,
    "post_noise_rms_mv": 0.0325639322400093,
    "post_vm_mv": -72.9258575439453,
    "pre_noise_rms_mv": 0.0465819016098976,
    "pre_vm_mv": -72.4875335693359,
    "slow_noise_rms_mv": 0.157671496272087,
    "slow_vm_mv": -72.4875335693359,
    "specimen_id": 328031983,
    "stimulus_absolute_amplitude": 579.999992478264,
    "stimulus_description": "C2SSTRIPLE141203[1]",
    "stimulus_duration": 0.024995,
    "stimulus_interval": 0.011,
    "stimulus_name": "Short Square - Triple",
    "stimulus_relative_amplitude": 5.8,
    "stimulus_start_time": 2.02,
    "stimulus_units": "Amps",
    "sweep_number": 94,
    "vm_delta_mv": 0.438323974609375
  },
  {
    "bridge_balance_mohm": 13.308913230896,
    "id": 396403276,
    "leak_pa": -20.9852848052979,
    "num_spikes": 3,
    "peak_deflection": null,
    "post_noise_rms_mv": 0.0392866544425488,
    "post_vm_mv": -72.8212509155273,
    "pre_noise_rms_mv": 0.0347009710967541,
    "pre_vm_mv": -72.4705123901367,
    "slow_noise_rms_mv": 0.137488305568695,
    "slow_vm_mv": -72.4705123901367,
    "specimen_id": 328031983,
    "stimulus_absolute_amplitude": 579.999992478264,
    "stimulus_description": "C2SSTRIPLE141203[2]",
    "stimulus_duration": 0.032995,
    "stimulus_interval": 0.015,
    "stimulus_name": "Short Square - Triple",
    "stimulus_relative_amplitude": 5.8,
    "stimulus_start_time": 2.02,
    "stimulus_units": "Amps",
    "sweep_number": 95,
    "vm_delta_mv": 0.350738525390625
  },
  {
    "bridge_balance_mohm": 13.308913230896,
    "id": 396403278,
    "leak_pa": -20.9852848052979,
    "num_spikes": 3,
    "peak_deflection": null,
    "post_noise_rms_mv": 0.0418970659375191,
    "post_vm_mv": -72.716682434082,
    "pre_noise_rms_mv": 0.0369276441633701,
    "pre_vm_mv": -72.2007369995117,
    "slow_noise_rms_mv": 0.0967089161276817,
    "slow_vm_mv": -72.2007369995117,
    "specimen_id": 328031983,
    "stimulus_absolute_amplitude": 579.999992478264,
    "stimulus_description": "C2SSTRIPLE141203[3]",
    "stimulus_duration": 0.040995,
    "stimulus_interval": 0.019,
    "stimulus_name": "Short Square - Triple",
    "stimulus_relative_amplitude": 5.8,
    "stimulus_start_time": 2.02,
    "stimulus_units": "Amps",
    "sweep_number": 96,
    "vm_delta_mv": 0.515945434570312
  },
  {
    "bridge_balance_mohm": 13.308913230896,
    "id": 396403280,
    "leak_pa": -20.9852848052979,
    "num_spikes": 3,
    "peak_deflection": null,
    "post_noise_rms_mv": 0.041076023131609,
    "post_vm_mv": -72.6434326171875,
    "pre_noise_rms_mv": 0.0370947681367397,
    "pre_vm_mv": -71.6391067504883,
    "slow_noise_rms_mv": 0.18281264603138,
    "slow_vm_mv": -71.6391067504883,
    "specimen_id": 328031983,
    "stimulus_absolute_amplitude": 579.999992478264,
    "stimulus_description": "C2SSTRIPLE141203[4]",
    "stimulus_duration": 0.048995,
    "stimulus_interval": 0.023,
    "stimulus_name": "Short Square - Triple",
    "stimulus_relative_amplitude": 5.8,
    "stimulus_start_time": 2.02,
    "stimulus_units": "Amps",
    "sweep_number": 97,
    "vm_delta_mv": 1.00432586669922
  },
  {
    "bridge_balance_mohm": 13.308913230896,
    "id": 396403282,
    "leak_pa": -20.9852848052979,
    "num_spikes": 3,
    "peak_deflection": null,
    "post_noise_rms_mv": 0.0392631664872169,
    "post_vm_mv": -72.7375411987305,
    "pre_noise_rms_mv": 0.0372799038887024,
    "pre_vm_mv": -72.2368698120117,
    "slow_noise_rms_mv": 0.120706781744957,
    "slow_vm_mv": -72.2368698120117,
    "specimen_id": 328031983,
    "stimulus_absolute_amplitude": 579.999992478264,
    "stimulus_description": "C2SSTRIPLE141203[5]",
    "stimulus_duration": 0.056995,
    "stimulus_interval": 0.027,
    "stimulus_name": "Short Square - Triple",
    "stimulus_relative_amplitude": 5.8,
    "stimulus_start_time": 2.02,
    "stimulus_units": "Amps",
    "sweep_number": 98,
    "vm_delta_mv": 0.50067138671875
  },
  {
    "bridge_balance_mohm": 13.308913230896,
    "id": 396403284,
    "leak_pa": -20.9852848052979,
    "num_spikes": 3,
    "peak_deflection": null,
    "post_noise_rms_mv": 0.0389445014297962,
    "post_vm_mv": -72.6048278808594,
    "pre_noise_rms_mv": 0.0456076972186565,
    "pre_vm_mv": -72.1915817260742,
    "slow_noise_rms_mv": 0.119005933403969,
    "slow_vm_mv": -72.1915817260742,
    "specimen_id": 328031983,
    "stimulus_absolute_amplitude": 579.999992478264,
    "stimulus_description": "C2SSTRIPLE141203[6]",
    "stimulus_duration": 0.064995,
    "stimulus_interval": 0.031,
    "stimulus_name": "Short Square - Triple",
    "stimulus_relative_amplitude": 5.8,
    "stimulus_start_time": 2.02,
    "stimulus_units": "Amps",
    "sweep_number": 99,
    "vm_delta_mv": 0.413246154785156
  },
  {
    "bridge_balance_mohm": 13.308913230896,
    "id": 396403057,
    "leak_pa": -20.9852848052979,
    "num_spikes": 3,
    "peak_deflection": null,
    "post_noise_rms_mv": 0.038661602884531,
    "post_vm_mv": -72.2412414550781,
    "pre_noise_rms_mv": 0.0390730127692223,
    "pre_vm_mv": -71.1963424682617,
    "slow_noise_rms_mv": 0.101248927414417,
    "slow_vm_mv": -71.1963424682617,
    "specimen_id": 328031983,
    "stimulus_absolute_amplitude": 579.999992478264,
    "stimulus_description": "C2SSTRIPLE141203[7]",
    "stimulus_duration": 0.072995,
    "stimulus_interval": 0.035,
    "stimulus_name": "Short Square - Triple",
    "stimulus_relative_amplitude": 5.8,
    "stimulus_start_time": 2.02,
    "stimulus_units": "Amps",
    "sweep_number": 100,
    "vm_delta_mv": 1.04489898681641
  },
  {
    "bridge_balance_mohm": 13.308913230896,
    "id": 396403059,
    "leak_pa": -20.9852848052979,
    "num_spikes": 0,
    "peak_deflection": null,
    "post_noise_rms_mv": 0.0,
    "post_vm_mv": 0.0,
    "pre_noise_rms_mv": 0.0,
    "pre_vm_mv": 0.0,
    "slow_noise_rms_mv": 0.0,
    "slow_vm_mv": 0.0,
    "specimen_id": 328031983,
    "stimulus_absolute_amplitude": 9.99999977648258,
    "stimulus_description": "EXTPEXPEND141203[0]",
    "stimulus_duration": 0.069995,
    "stimulus_interval": 0.05,
    "stimulus_name": "Test",
    "stimulus_relative_amplitude": 1.0,
    "stimulus_start_time": 0.03,
    "stimulus_units": "Volts",
    "sweep_number": 101,
    "vm_delta_mv": 0.0
  },
  {
    "bridge_balance_mohm": 13.308913230896,
    "id": 396403061,
    "leak_pa": -20.9852848052979,
    "num_spikes": 0,
    "peak_deflection": null,
    "post_noise_rms_mv": 0.0,
    "post_vm_mv": 0.0,
    "pre_noise_rms_mv": 0.0,
    "pre_vm_mv": 0.0,
    "slow_noise_rms_mv": 0.0,
    "slow_vm_mv": 0.0,
    "specimen_id": 328031983,
    "stimulus_absolute_amplitude": 9.99999977648258,
    "stimulus_description": "EXTPGGAEND141203[0]",
    "stimulus_duration": 0.069995,
    "stimulus_interval": 0.05,
    "stimulus_name": "Test",
    "stimulus_relative_amplitude": 1.0,
    "stimulus_start_time": 0.03,
    "stimulus_units": "Volts",
    "sweep_number": 102,
    "vm_delta_mv": 0.0
  },
  {
    "bridge_balance_mohm": 0.0,
    "id": 396403063,
    "leak_pa": 0.0,
    "num_spikes": null,
    "peak_deflection": null,
    "post_noise_rms_mv": 0.0416472442448139,
    "post_vm_mv": 0.600544989109039,
    "pre_noise_rms_mv": 0.0343364849686623,
    "pre_vm_mv": 0.538587093353271,
    "slow_noise_rms_mv": 0.0526617653667927,
    "slow_vm_mv": 0.538587093353271,
    "specimen_id": 328031983,
    "stimulus_absolute_amplitude": 0.0,
    "stimulus_description": "EXTPBLWOUT141203[0]",
    "stimulus_duration": 0.0,
    "stimulus_interval": null,
    "stimulus_name": "Test",
    "stimulus_relative_amplitude": 1.0,
    "stimulus_start_time": 0.0,
    "stimulus_units": "Amps",
    "sweep_number": 103,
    "vm_delta_mv": 0.0619578957557678
  }
]